datasette_tailwindcss/__init__.py
datasette_tailwindcss/static/tailwindcss_v3_3_3.js
datasette_tailwindcss/templates/_close_open_menus.html
datasette_tailwindcss/templates/_codemirror.html
datasette_tailwindcss/templates/_codemirror_foot.html
datasette_tailwindcss/templates/_crumbs.html
datasette_tailwindcss/templates/_description_source_license.html
datasette_tailwindcss/templates/_facet_results.html
datasette_tailwindcss/templates/_footer.html
datasette_tailwindcss/templates/_suggested_facets.html
datasette_tailwindcss/templates/_table.html
datasette_tailwindcss/templates/allow_debug.html
datasette_tailwindcss/templates/api_explorer.html
datasette_tailwindcss/templates/base.html
datasette_tailwindcss/templates/create_token.html
datasette_tailwindcss/templates/database.html
datasette_tailwindcss/templates/error.html
datasette_tailwindcss/templates/index.html
datasette_tailwindcss/templates/logout.html
datasette_tailwindcss/templates/messages_debug.html
datasette_tailwindcss/templates/patterns.html
datasette_tailwindcss/templates/permissions_debug.html
datasette_tailwindcss/templates/query.html
datasette_tailwindcss/templates/row.html
datasette_tailwindcss/templates/show_json.html
datasette_tailwindcss/templates/table.html
datasette_tailwindcss-0.1.dist-info/LICENSE
datasette_tailwindcss-0.1.dist-info/METADATA
datasette_tailwindcss-0.1.dist-info/WHEEL
datasette_tailwindcss-0.1.dist-info/entry_points.txt
datasette_tailwindcss-0.1.dist-info/top_level.txt
datasette_tailwindcss-0.1.dist-info/RECORD
