Metadata-Version: 2.1
Name: datasette-tailwindcss
Version: 0.1
Summary: Replace default template with tailwindcss
Home-page: https://github.com/publicmatt/datasette-tailwindcss
Author: matt jensen
License: Apache License, Version 2.0
Project-URL: Issues, https://github.com/publicmatt/datasette-tailwindcss/issues
Project-URL: CI, https://github.com/publicmatt/datasette-tailwindcss/actions
Project-URL: Changelog, https://github.com/publicmatt/datasette-tailwindcss/releases
Classifier: Framework :: Datasette
Classifier: License :: OSI Approved :: Apache Software License
Requires-Python: >=3.7
License-File: LICENSE
Requires-Dist: datasette
Provides-Extra: test
Requires-Dist: pytest ; extra == 'test'
Requires-Dist: pytest-asyncio ; extra == 'test'
